README.txt
setup.py
checkselect/__init__.py
checkselect/release.py
checkselect/widgets.py
checkselect.egg-info/PKG-INFO
checkselect.egg-info/SOURCES.txt
checkselect.egg-info/dependency_links.txt
checkselect.egg-info/entry_points.txt
checkselect.egg-info/not-zip-safe
checkselect.egg-info/requires.txt
checkselect.egg-info/top_level.txt
checkselect/static/css/checkselect.css
checkselect/static/images/bin_empty.png
checkselect/static/images/page_new.gif
checkselect/static/javascript/checkselect.js
checkselect/templates/__init__.py
checkselect/templates/checkselect.kid
checkselect/templates/checkselectadd.kid
