Metadata-Version: 1.0
Name: checkselect
Version: 1.2
Summary: CheckSelect TurboGears Widget
Home-page: http://public-trac.godoy.homeip.net/trac/checkselect/
Author: Jorge Godoy
Author-email: jgodoy@gmail.com
License: MIT
Keywords: turbogears.widgets
Platform: UNKNOWN
Classifier: Development Status :: 3 - Alpha
Classifier: Operating System :: OS Independent
Classifier: Programming Language :: Python
Classifier: Topic :: Software Development :: Libraries :: Python Modules
Classifier: Framework :: TurboGears
Classifier: Framework :: TurboGears :: Widgets
